{
  "thing": {
    "name": "IKEA Samla Tray Insert Wedge NG Parametric",
    "category": "Other",
    "tags": [
      "parametric",
      "openscad",
      "IKEA",
      "Samla"
    ],
    "is_wip": false,
    "license": "bsd",
    "id": 6526779
  },
  "files": {
    "output/ikea-samla-wedge-ng-parametric-Big.stl": {
      "id": 14284368,
      "name": "ikea-samla-wedge-ng-parametric-Big.stl",
      "url": "https://www.thingiverse.com/download:14284368"
    },
    "output/ikea-samla-wedge-ng-parametric-Small.stl": {
      "id": 14284369,
      "name": "ikea-samla-wedge-ng-parametric-Small.stl",
      "url": "https://www.thingiverse.com/download:14284369"
    },
    "ikea-samla-wedge-ng-parametric.scad": {},
    "ikea-samla-wedge-ng-parametric.json": {}
  },
  "images": {}
}